rememberCLI/__init__.py
rememberCLI/main.py
remembercli-0.1.14.dist-info/METADATA
remembercli-0.1.14.dist-info/WHEEL
remembercli-0.1.14.dist-info/entry_points.txt
remembercli-0.1.14.dist-info/licenses/LICENSE.md
remembercli-0.1.14.dist-info/RECORD
