Metadata-Version: 2.4
Name: remembercli
Version: 0.1.14
Summary: A CLI-based task management tool for the distracted!
License-File: LICENSE.md
Requires-Python: >=3.12
Requires-Dist: dateparser>=1.2.0
Requires-Dist: python-dateutil>=2.9.0.post0
Requires-Dist: typer>=0.15.1
